getx/__init__.py
getx/subs.py
getx-0.1.1.dist-info/METADATA
getx-0.1.1.dist-info/WHEEL
getx-0.1.1.dist-info/RECORD
