Metadata-Version: 2.1
Name: getx
Version: 0.1.1
Summary: 
Author: Elsafy Hegazy
Author-email: safy.dev@gmail.com
Requires-Python: >=3.11,<4.0
Classifier: Programming Language :: Python :: 3
Classifier: Programming Language :: Python :: 3.11
Requires-Dist: cryptography (>=39.0.1,<40.0.0)
Requires-Dist: requests (>=2.28.2,<3.0.0)
